itermspace/__init__.py
itermspace/__main__.py
itermspace/cli.py
itermspace/config.py
itermspace/exceptions.py
itermspace/iterm_adapter.py
itermspace/layout.py
itermspace/preview.py
itermspace-0.0.1.dist-info/METADATA
itermspace-0.0.1.dist-info/WHEEL
itermspace-0.0.1.dist-info/entry_points.txt
itermspace-0.0.1.dist-info/licenses/LICENSE
itermspace-0.0.1.dist-info/RECORD
