Metadata-Version: 2.4
Name: itermspace
Version: 0.0.1
Summary: Launch iTerm2 workspaces from YAML configuration
Author-email: midodimori <midodimori@users.noreply.github.com>
License: MIT
License-File: LICENSE
Requires-Python: >=3.13
Requires-Dist: iterm2>=2.13
Requires-Dist: pydantic>=2.12.5
Requires-Dist: pyyaml>=6.0.3
